alcatel_modem_api/__init__.py
alcatel_modem_api/cli.py
alcatel_modem_api/client.py
alcatel_modem_api/config.py
alcatel_modem_api/constants.py
alcatel_modem_api/exceptions.py
alcatel_modem_api/models.py
alcatel_modem_api/py.typed
alcatel_modem_api/auth/__init__.py
alcatel_modem_api/auth/strategies.py
alcatel_modem_api/endpoints/__init__.py
alcatel_modem_api/endpoints/device.py
alcatel_modem_api/endpoints/network.py
alcatel_modem_api/endpoints/sms.py
alcatel_modem_api/endpoints/system.py
alcatel_modem_api/endpoints/wlan.py
alcatel_modem_api/utils/__init__.py
alcatel_modem_api/utils/diagnostics.py
alcatel_modem_api/utils/diagnostics_models.py
alcatel_modem_api/utils/display.py
alcatel_modem_api/utils/encryption.py
alcatel_modem_api/utils/keyring_storage.py
alcatel_modem_api/utils/logging.py
alcatel_modem_api-0.1.0.dist-info/METADATA
alcatel_modem_api-0.1.0.dist-info/WHEEL
alcatel_modem_api-0.1.0.dist-info/entry_points.txt
alcatel_modem_api-0.1.0.dist-info/licenses/LICENSE
alcatel_modem_api-0.1.0.dist-info/RECORD
