Metadata-Version: 2.4
Name: alcatel-modem-api
Version: 0.1.0
Summary: Generic Python library and CLI tool for Alcatel LTE modems
Project-URL: Homepage, https://github.com/volkanncicek/alcatel-modem-api
Project-URL: Repository, https://github.com/volkanncicek/alcatel-modem-api
Project-URL: Issues, https://github.com/volkanncicek/alcatel-modem-api/issues
Project-URL: Changelog, https://github.com/volkanncicek/alcatel-modem-api/blob/main/CHANGELOG.md
Author: Alcatel Modem API Contributors
License: MIT
License-File: LICENSE
Keywords: 4g,5g,alcatel,api,lte,modem,router,sms
Classifier: Development Status :: 4 - Beta
Classifier: Intended Audience :: Developers
Classifier: License :: OSI Approved :: MIT License
Classifier: Programming Language :: Python :: 3
Classifier: Programming Language :: Python :: 3.9
Classifier: Programming Language :: Python :: 3.10
Classifier: Programming Language :: Python :: 3.11
Classifier: Programming Language :: Python :: 3.12
Classifier: Topic :: Communications :: Telephony
Classifier: Topic :: System :: Networking
Requires-Python: >=3.9
Requires-Dist: cryptography>=3.4.8
Requires-Dist: httpx>=0.25.0
Requires-Dist: keyring>=24.0.0
Requires-Dist: platformdirs>=4.0.0
Requires-Dist: pydantic>=2.0.0
Requires-Dist: rich>=13.0.0
Requires-Dist: tomli-w>=1.0.0
Requires-Dist: tomli>=2.0.0; python_version < '3.11'
Requires-Dist: typer>=0.9.0
Provides-Extra: dev
Requires-Dist: bandit[toml]>=1.7.0; extra == 'dev'
Requires-Dist: hypothesis>=6.0.0; extra == 'dev'
Requires-Dist: mypy>=1.5.0; extra == 'dev'
Requires-Dist: pre-commit>=3.0.0; extra == 'dev'
Requires-Dist: pytest-cov>=4.0.0; extra == 'dev'
Requires-Dist: pytest>=7.0.0; extra == 'dev'
Requires-Dist: respx>=0.20.0; extra == 'dev'
Requires-Dist: ruff>=0.1.0; extra == 'dev'
Requires-Dist: tomli>=2.0.0; extra == 'dev'
